whiscraper/__init__.py
whiscraper/browser/browser_manager.py
whiscraper/browser/context.py
whiscraper/browser/page.py
whiscraper/browser/extensions/cf-captcha-solver.crx
whiscraper/browser/tools/__init__.py
whiscraper/browser/tools/captcha_solver.py
whiscraper/browser/tools/request_interceptor.py
whiscraper-0.2.0.dist-info/METADATA
whiscraper-0.2.0.dist-info/WHEEL
whiscraper-0.2.0.dist-info/RECORD
