Metadata-Version: 2.4
Name: whiscraper
Version: 0.2.0
Summary: Your Stealthy Scraping Python Framework
Requires-Python: >=3.9
Requires-Dist: nodriver>=0.38
